FISH_analysis/__init__.py
FISH_analysis/cell_segmentation.py
FISH_analysis/puncta_analysis.py
FISH_analysis/puncta_thresholding.py
FISH_analysis-0.0.1.dist-info/METADATA
FISH_analysis-0.0.1.dist-info/WHEEL
FISH_analysis-0.0.1.dist-info/top_level.txt
FISH_analysis-0.0.1.dist-info/RECORD
