Metadata-Version: 2.1
Name: FISH-analysis
Version: 0.0.1
Summary: FISH image analysis library
Home-page: https://github.com/Sreevatsa03/FISH-Image-Analysis
Author: Sreevatsa Nukala, Kate Hudson, Antonio Villaneuva, Soumili Dey, Joseph Entner
Author-email: sreevatsa.nukala@gmail.com
License: UNKNOWN
Platform: UNKNOWN
Classifier: Intended Audience :: Science/Research
Classifier: Intended Audience :: Healthcare Industry
Classifier: Programming Language :: Python
Classifier: Programming Language :: Python :: 3
Classifier: Programming Language :: Python :: 3.8
Classifier: Programming Language :: Python :: 3.9
Classifier: Operating System :: OS Independent
Classifier: Topic :: Scientific/Engineering :: Bio-Informatics
Classifier: Topic :: Scientific/Engineering :: Image Processing
Requires-Dist: numpy
Requires-Dist: cellpose
Requires-Dist: Pillow
Requires-Dist: matplotlib
Requires-Dist: os
Requires-Dist: opencv-python
Requires-Dist: scikit-learn
